pansys/__init__.py
pansys/interactive.py
pansys/utility_functions.py
pansys/tests/__init__.py
pansys/tests/tests.py
pansys/tests/tests_ssh.py
pansys-0.1.3.dist-info/METADATA
pansys-0.1.3.dist-info/RECORD
pansys-0.1.3.dist-info/WHEEL
pansys-0.1.3.dist-info/top_level.txt
