Metadata-Version: 2.1
Name: pansys
Version: 0.1.3
Summary: Work with Ansys through python
Home-page: https://github.com/idling-mind/pansys
Author: Najeem Muhammed
Author-email: najeem@gmail.com
License: UNKNOWN
Platform: UNKNOWN
Classifier: Development Status :: 3 - Alpha
Classifier: Programming Language :: Python :: 3
Classifier: License :: OSI Approved :: MIT License
Classifier: Operating System :: POSIX
Classifier: Topic :: Scientific/Engineering
Requires-Dist: pexpect
Requires-Dist: pandas
